zack_puc_ia_csv_converter/__init__.py
zack_puc_ia_csv_converter/converter.py
zack_puc_ia_csv_converter/file_1.csv
zack_puc_ia_csv_converter/file_2.csv
zack_puc_ia_csv_converter-0.1.9.dist-info/entry_points.txt
zack_puc_ia_csv_converter-0.1.9.dist-info/WHEEL
zack_puc_ia_csv_converter-0.1.9.dist-info/METADATA
zack_puc_ia_csv_converter-0.1.9.dist-info/RECORD
