Metadata-Version: 2.1
Name: zack-puc-ia-csv-converter
Version: 0.1.9
Summary: Convert CSV to JSON or JSON to CSV
Author: ezequiel lima 
Author-email: ezekiel_lima@hotmail.com
Requires-Python: >=3.8,<4.0
Classifier: Programming Language :: Python :: 3
Classifier: Programming Language :: Python :: 3.10
Classifier: Programming Language :: Python :: 3.8
Classifier: Programming Language :: Python :: 3.9
Requires-Dist: click (>=8.0.3,<9.0.0)
Requires-Dist: pandas (>=1.3.5,<2.0.0)
